content_view/__init__.py
content_view/main.py
content_view-0.1.0.dist-info/LICENSE
content_view-0.1.0.dist-info/METADATA
content_view-0.1.0.dist-info/WHEEL
content_view-0.1.0.dist-info/top_level.txt
content_view-0.1.0.dist-info/RECORD
