Metadata-Version: 2.1
Name: content-view
Version: 0.1.0
Summary: A short description of your Tkinter package
Author: Dawei Wang
Author-email: wangdawei1104@gmail.com
Classifier: Programming Language :: Python :: 3
Classifier: License :: OSI Approved :: MIT License
Classifier: Operating System :: OS Independent
Requires-Python: >=3.6
License-File: LICENSE
